on2vec/__init__.py
on2vec/batch_hf_models.py
on2vec/benchmarks.py
on2vec/cli.py
on2vec/cli_utils.py
on2vec/config.py
on2vec/device_utils.py
on2vec/embedding.py
on2vec/evaluation.py
on2vec/huggingface_workflows.py
on2vec/io.py
on2vec/loss_functions.py
on2vec/metadata_utils.py
on2vec/model_card_generator.py
on2vec/model_comparison.py
on2vec/models.py
on2vec/ontology.py
on2vec/query_document_ontology_model.py
on2vec/sentence_transformer_hub.py
on2vec/sentence_transformer_hub.py.backup
on2vec/sentence_transformer_integration.py
on2vec/text_features.py
on2vec/training.py
on2vec/visualization.py
on2vec/workflows.py
on2vec-0.1.1.dist-info/METADATA
on2vec-0.1.1.dist-info/WHEEL
on2vec-0.1.1.dist-info/entry_points.txt
on2vec-0.1.1.dist-info/licenses/LICENSE
on2vec-0.1.1.dist-info/RECORD
