Metadata-Version: 2.4
Name: on2vec
Version: 0.1.1
Summary: Generate vector embeddings from OWL ontologies using Graph Neural Networks with HuggingFace integration and MTEB benchmarking
Project-URL: Homepage, https://github.com/david4096/on2vec
Project-URL: Repository, https://github.com/david4096/on2vec
Project-URL: Issues, https://github.com/david4096/on2vec/issues
Project-URL: Documentation, https://github.com/david4096/on2vec/blob/main/README.md
Author-email: David Steinberg <david@resium.com>
Maintainer-email: David Steinberg <david@resium.com>
License: MIT
License-File: LICENSE
Keywords: embeddings,graph-neural-networks,huggingface,machine-learning,mteb,ontology,owl,sentence-transformers
Classifier: Development Status :: 3 - Alpha
Classifier: Intended Audience :: Science/Research
Classifier: License :: OSI Approved :: MIT License
Classifier: Programming Language :: Python :: 3
Classifier: Programming Language :: Python :: 3.10
Classifier: Programming Language :: Python :: 3.11
Classifier: Programming Language :: Python :: 3.12
Classifier: Topic :: Scientific/Engineering :: Artificial Intelligence
Classifier: Topic :: Scientific/Engineering :: Information Analysis
Classifier: Topic :: Text Processing :: Linguistic
Requires-Python: >=3.10
Requires-Dist: graphviz>=0.20.0
Requires-Dist: huggingface-hub>=0.15.0
Requires-Dist: matplotlib>=3.5.0
Requires-Dist: mteb>=1.38.54
Requires-Dist: networkx>=3.0.0
Requires-Dist: owlready2>=0.45
Requires-Dist: pandas>=2.0.0
Requires-Dist: plotly>=5.0.0
Requires-Dist: polars>=0.20.0
Requires-Dist: pyarrow>=10.0.0
Requires-Dist: pydot>=2.0.0
Requires-Dist: pyyaml>=6.0.0
Requires-Dist: scikit-learn>=1.2.0
Requires-Dist: seaborn>=0.11.0
Requires-Dist: sentence-transformers>=2.2.0
Requires-Dist: torch-geometric>=2.3.0
Requires-Dist: torch>=2.0.0
Requires-Dist: transformers>=4.21.0
Requires-Dist: twine>=6.2.0
Requires-Dist: umap-learn>=0.5.0
Provides-Extra: all
Requires-Dist: black>=23.0; extra == 'all'
Requires-Dist: flake8>=6.0; extra == 'all'
Requires-Dist: ipywidgets>=8.0.0; extra == 'all'
Requires-Dist: isort>=5.12; extra == 'all'
Requires-Dist: jupyter>=1.0.0; extra == 'all'
Requires-Dist: jupyterlab>=4.0.0; extra == 'all'
Requires-Dist: mteb>=1.0.0; extra == 'all'
Requires-Dist: mypy>=1.0; extra == 'all'
Requires-Dist: pytest-cov>=4.0; extra == 'all'
Requires-Dist: pytest>=7.0; extra == 'all'
Requires-Dist: requests>=2.28.0; extra == 'all'
Provides-Extra: benchmark
Requires-Dist: mteb>=1.0.0; extra == 'benchmark'
Provides-Extra: dev
Requires-Dist: black>=22.0; extra == 'dev'
Requires-Dist: flake8>=5.0; extra == 'dev'
Requires-Dist: isort>=5.10; extra == 'dev'
Requires-Dist: mypy>=0.950; extra == 'dev'
Requires-Dist: pytest-cov>=3.0; extra == 'dev'
Requires-Dist: pytest>=6.0; extra == 'dev'
Provides-Extra: notebook
Requires-Dist: ipywidgets>=8.0.0; extra == 'notebook'
Requires-Dist: jupyter>=1.0.0; extra == 'notebook'
Requires-Dist: jupyterlab>=4.0.0; extra == 'notebook'
Requires-Dist: requests>=2.28.0; extra == 'notebook'
